fmpclient/__init__.py
fmpclient-0.1.1.dist-info/LICENSE.txt
fmpclient-0.1.1.dist-info/METADATA
fmpclient-0.1.1.dist-info/WHEEL
fmpclient-0.1.1.dist-info/top_level.txt
fmpclient-0.1.1.dist-info/RECORD
