Metadata-Version: 2.1
Name: fmpclient
Version: 0.1.1
Summary: A FinancialModellingPrep API wrapper.
Home-page: https://github.com/iainwo/fmpclient
Author: Iain Wong
Author-email: iainwong@outlook.com
License: MIT License
Download-URL: https://github.com/iainwo/fmpclient/archive/v0.1.1.tar.gz
Keywords: investing,finance,api,valuation,wrapper,client
Platform: UNKNOWN
Classifier: Development Status :: 3 - Alpha
Classifier: Intended Audience :: Developers
Classifier: Topic :: Software Development :: Build Tools
Classifier: License :: OSI Approved :: MIT License
Classifier: Programming Language :: Python :: 3
Requires-Dist: requests
